<TABLE><ROW><SITNAME>EII_Current_MsgStats</SITNAME><FULLNAME><![CDATA[]]></FULLNAME><ADVISE><![CDATA[*NONE]]></ADVISE><AFFINITIES><![CDATA[%IBM.STATIC022          0000000003#########]]></AFFINITIES><ALERTLIST></ALERTLIST><AUTOSOPT>NNN</AUTOSOPT><AUTOSTART>*YES</AUTOSTART><CMD><![CDATA[*NONE]]></CMD><DESTNODE></DESTNODE><HUB></HUB><LOCFLAG></LOCFLAG><LSTCCSID>en_US</LSTCCSID><LSTDATE>1220223133913000</LSTDATE><LSTRELEASE>V100</LSTRELEASE><LSTUSRPRF>A459221</LSTUSRPRF><NOTIFYARGS></NOTIFYARGS><NOTIFYOPTS></NOTIFYOPTS><OBJECTLOCK></OBJECTLOCK><PDT><![CDATA[*IF *VALUE Message_Statistics.Queue_Name *EQ QEIEP.P001.NGCLAIMS.CCFMQBCKUP *AND *VALUE Message_Statistics.Total_Messages *GT 0]]></PDT><PRNAMES></PRNAMES><QIBSCOPE>E</QIBSCOPE><REEV_DAYS>0</REEV_DAYS><REEV_TIME>000100</REEV_TIME><REFLEXOK></REFLEXOK><SENDMSGQ>*NONE</SENDMSGQ><SITINFO><![CDATA[TFWD=Y;SEV=Informational;TDST=2;~;]]></SITINFO><SOURCE></SOURCE><TEXT><![CDATA[]]></TEXT></ROW><ROW>
<ID>EII_Current_MsgStats</ID>
<OBJCLASS>2250</OBJCLASS>
<SEQUENCE>9999</SEQUENCE>
<TYPE></TYPE>
<LSTDATE>1220302100920000</LSTDATE>
<LSTUSRPRF>A459221</LSTUSRPRF>
<LSTRELEASE></LSTRELEASE>
<LOCFLAG></LOCFLAG>
<RESERVED></RESERVED>
<MAP><![CDATA[<situation name="EII_Current_MsgStats"  ><class name="ITM_Message_Statistics" /><slot slotName="msg" ><literalString value="MQ--Queue $Message_Statistics.Queue_Name$ Has A New Message That Is $Message_Statistics.Newest_Message_Seconds$ Old, Total Msgs=$Message_Statistics.Total_Messages$" /></slot><slot slotName="msg_catalog" ><literalString value="noshow" /></slot><slot slotName="NotifyAction" ><literalString value="11" /></slot><slot slotName="NotifyCategory" ><literalString value="2" /></slot><slot slotName="NotifyEmailGroup" ><literalString value="username@email.com" /></slot></situation>]]></MAP>
</ROW>
</TABLE>
